autodiff/AD.py
autodiff/__init__.py
autodiff/reverse.py
GuruDiff-1.0.0.dist-info/METADATA
GuruDiff-1.0.0.dist-info/WHEEL
GuruDiff-1.0.0.dist-info/top_level.txt
GuruDiff-1.0.0.dist-info/RECORD
