Metadata-Version: 2.1
Name: GuruDiff
Version: 1.0.0
Summary: A easy-used auto-differentiation package, supporting both forward mode and reverse mode
Home-page: https://https://github.com/Software-Samurais/cs207-FinalProject
Author: Erick Ruiz, Jingyuan Liu, Simon (Xin) Dong, Kailas Amin
Author-email: eruiz@g.harvard.edu, jingyuanliu@g.harvard.edu, xindong@g.harvard.edu, kailasamin@college.harvard.edu
License: UNKNOWN
Platform: UNKNOWN
Classifier: Programming Language :: Python :: 3
Classifier: License :: OSI Approved :: MIT License
Classifier: Operating System :: OS Independent
Requires-Python: >=3.6
Requires-Dist: numpy (==1.17.3)
Requires-Dist: pytest (==5.2.2)
